ip_logger/__init__.py
ip_logger/admin.py
ip_logger/apps.py
ip_logger/middleware.py
ip_logger/models.py
ip_logger/tests.py
ip_logger/urls.py
ip_logger/utils.py
ip_logger/views.py
ip_logger/migrations/0001_initial.py
ip_logger/migrations/__init__.py
django_ip_logger-1.0.1.dist-info/LICENSE
django_ip_logger-1.0.1.dist-info/METADATA
django_ip_logger-1.0.1.dist-info/WHEEL
django_ip_logger-1.0.1.dist-info/top_level.txt
django_ip_logger-1.0.1.dist-info/RECORD
